pdfly/__init__.py
pdfly/__main__.py
pdfly/_utils.py
pdfly/_version.py
pdfly/booklet.py
pdfly/cat.py
pdfly/check_sign.py
pdfly/cli.py
pdfly/compress.py
pdfly/extract_annotated_pages.py
pdfly/extract_images.py
pdfly/metadata.py
pdfly/pagemeta.py
pdfly/rm.py
pdfly/rotate.py
pdfly/sign.py
pdfly/uncompress.py
pdfly/up2.py
pdfly/update_offsets.py
pdfly/x2pdf.py
pdfly-0.5.0.dist-info/entry_points.txt
pdfly-0.5.0.dist-info/licenses/LICENSE
pdfly-0.5.0.dist-info/WHEEL
pdfly-0.5.0.dist-info/METADATA
pdfly-0.5.0.dist-info/RECORD
