Metadata-Version: 2.4
Name: pdfly
Version: 0.5.0
Summary: A pure-python CLI application to manipulate PDF files
Author-email: Martin Thoma <info@martin-thoma.de>
Maintainer-email: Martin Thoma <info@martin-thoma.de>
Requires-Python: >=3.10.0
Classifier: Development Status :: 1 - Planning
Classifier: Environment :: Console
Classifier: Intended Audience :: Developers
Classifier: License :: OSI Approved :: BSD License
Classifier: Natural Language :: English
Classifier: Operating System :: OS Independent
Classifier: Programming Language :: Python :: 3
Classifier: Programming Language :: Python :: 3 :: Only
Classifier: Programming Language :: Python :: 3.10
Classifier: Programming Language :: Python :: 3.11
Classifier: Programming Language :: Python :: 3.12
Classifier: Programming Language :: Python :: 3.13
License-File: LICENSE
Requires-Dist: pypdf[full]>=5.1.0
Requires-Dist: typer>=0.12.4
Requires-Dist: pillow
Requires-Dist: pydantic
Requires-Dist: rich
Requires-Dist: fpdf2>=2.8.1
Requires-Dist: asn1crypto
Requires-Dist: cryptography
Requires-Dist: endesive
Project-URL: Source, https://github.com/py-pdf/pdfly
